puddy/__init__.py
puddy/readers.py
puddy/trajectory_analyzer.py
puddy/trajectory_collection.py
puddy-0.1.4.dist-info/licenses/LICENSE.txt
puddy-0.1.4.dist-info/METADATA
puddy-0.1.4.dist-info/WHEEL
puddy-0.1.4.dist-info/top_level.txt
puddy-0.1.4.dist-info/RECORD
