Metadata-Version: 2.4
Name: puddy
Version: 0.1.4
Summary: A toolkit for analyzing spatial trajectories
Author-email: Jason Frazier <jasonxfrazier@gmail.com>
License: MIT
License-File: LICENSE.txt
Requires-Dist: ijson
Requires-Dist: pandas
Requires-Dist: pyarrow
Requires-Dist: pytest
Requires-Dist: black
Requires-Dist: isort
Requires-Dist: ruff
Requires-Dist: mypy
Requires-Dist: PyYAML
Requires-Dist: types-PyYAML
Requires-Dist: numpy
Requires-Dist: scikit-learn
Requires-Dist: matplotlib
Dynamic: license-file
